Workbook

Sheet Sobre
B2: ESTUDO DE VIABILIDADE ECONÔMICA — PLANNERS (BRASIL)
B3: Investimento inicial R$ 5.000 · 2 SKUs (Concurseiro / Treino) · Fase 1 (produção nacional)
B4: Gerado em 19/jun/2026 · Câmbio de planejamento USD/BRL ≈ R$ 5,20
B6: COMO USAR
B7: 1. Edite SOMENTE as células AZUIS na aba "Premissas". Todo o resto recalcula sozinho.
B8: 2. "Unit Economics" mostra a margem por canal (Direto x Marketplace x Blended).
B9: 3. "Viabilidade" responde: o lote inicial recupera os R$ 5.000? A que % de venda?
B10: 4. "Cenários" compara Conservador / Base / Otimista (preço, custo, canal, sell-through).
B11: 5. "Projeção 12M" mostra a trajetória de resultado ao longo do 1º ano.
B13: LEGENDA DE CORES
B14: Azul = entradas editáveis | Preto = fórmulas | Verde = links entre abas | Amarelo = confirmar/atenção
B16: FONTES (datadas — jun/2026)
... B24: Estimativas para apoio à decisão. Custos de produção devem ser confirmados por orçamento de gráfica; tributos/MEI por contador. Não constitui recomendação financeira.

Sheet Premissas
A1: PREMISSAS — edite apenas as células azuis
A2: Investimento
A3: Material / 1º lote (R$) | B3: 3000
A4: Marketing & teste (R$) | B4: 2000
A5: Investimento total (R$) | B5: =B3+B4 -> 5000
A6: Produto & preço
A7: Preço de venda ao consumidor (R$) | B7: 119 | C7: posicionado ~15% acima do Juspodivm (premium/perpétuo)
A8: Custo unitário — produção nacional micro-lote (R$) | B8: 45 | C8: Tier B intermediário; Tier A premium ~R$ 50–58
A9: Unidades produzidas no 1º lote (un) | B9: =ROUNDDOWN(B3/B8,0) -> 66
A10: Canais de venda
A11: Mix — % vendas canal direto | B11: 0.9 | C11: Instagram + checkout próprio + pix
A12: Mix — % vendas marketplace | B12: =1-B11 -> 0.1
A13: Comissão marketplace (% s/ preço) | B13: 0.165 | C13: ML Premium papelaria ~16,5%
A14: Taxa fixa marketplace (R$/item) | B14: 20 | C14: faixa R$ 100–199,99 (Shopee 2026)
A15: Custo frete grátis marketplace (R$/venda) | B15: 18 | C15: obrigatório p/ itens ≥ R$ 79
A16: Taxa de pagamento — canal direto (% s/ preço) | B16: 0.025 | C16: blend pix (~1%) / cartão (~4%)
A17: Frete canal direto pago pela loja (R$) | B17: 0 | C17: cliente paga o frete
A18: Operacional & tributário
A19: Embalagem & manuseio por pedido (R$) | B19: 4
A20: Provisão devoluções/perdas (% s/ preço) | B20: 0.04
A21: DAS MEI mensal (R$) | B21: 80 | C21: CONFIRMAR 2026 (~5% do salário mín. + R$ 1)
A22: Meses do 1º ciclo | B22: 3
A23: Aquisição (teste pago)
A24: CAC médio pago no teste (R$/cliente) | B24: 45 | C24: Meta Ads: CPC R$ 1,5–3 / conv. 1–3%
A25: Verba de mídia paga (R$) | B25: 1200 | C25: parte dos R$ 2.000 de teste
A26: Clientes via mídia paga (estimativa) | B26: =ROUNDDOWN(B25/B24,0) -> 26

Sheet Unit Economics
A1: UNIT ECONOMICS (por unidade vendida) — R$
B2: Canal Direto | C2: Marketplace | D2: Blended (mix)
A3: Preço de venda | B3: =Premissas!$B$7 -> 119 | C3: =Premissas!$B$7 -> 119 | D3: =B3*Premissas!$B$11+C3*Premissas!$B$12 -> 119
A4: (−) Comissão marketplace | B4: =0 -> 0 | C4: =C3*Premissas!$B$13 -> 19.635 | D4: =B4*Premissas!$B$11+C4*Premissas!$B$12 -> 1.9635
A5: (−) Taxa fixa marketplace | B5: =0 -> 0 | C5: =Premissas!$B$14 -> 20 | D5: =B5*Premissas!$B$11+C5*Premissas!$B$12 -> 2
A6: (−) Frete (custo p/ loja) | B6: =Premissas!$B$17 -> 0 | C6: =Premissas!$B$15 -> 18 | D6: =B6*Premissas!$B$11+C6*Premissas!$B$12 -> 1.8
A7: (−) Taxa de pagamento | B7: =B3*Premissas!$B$16 -> 2.975 | C7: =0 -> 0 | D7: =B7*Premissas!$B$11+C7*Premissas!$B$12 -> 2.6775
A8: (−) Embalagem & manuseio | B8: =Premissas!$B$19 -> 4 | C8: =Premissas!$B$19 -> 4 | D8: =B8*Premissas!$B$11+C8*Premissas!$B$12 -> 4
A9: (−) Provisão devoluções | B9: =B3*Premissas!$B$20 -> 4.76 | C9: =C3*Premissas!$B$20 -> 4.76 | D9: =B9*Premissas!$B$11+C9*Premissas!$B$12 -> 4.76
A10: (=) Contribuição/un vendida (excl. produto) | B10: =B3-SUM(B4:B9) -> 107.265 | C10: =C3-SUM(C4:C9) -> 52.605 | D10: =B10*Premissas!$B$11+C10*Premissas!$B$12 -> 101.799
A11: (−) Custo do produto | B11: =Premissas!$B$8 -> 45 | C11: =Premissas!$B$8 -> 45 | D11: =B11*Premissas!$B$11+C11*Premissas!$B$12 -> 45
A12: (=) Margem de contribuição (com produto) | B12: =B10-B11 -> 62.265 | C12: =C10-C11 -> 7.605 | D12: =B12*Premissas!$B$11+C12*Premissas!$B$12 -> 56.799
A13: Margem de contribuição (%) | B13: =B12/B3 -> 0.52323529 | C13: =C12/C3 -> 0.063907563 | D13: =D12/D3 -> 0.47730252
A15: Observação: a R$ 119, o marketplace consome ~48% do preço em taxas+frete — margem quase nula. O canal direto preserva a margem. Fase 1 = vender direto.

Sheet Viabilidade
A1: VIABILIDADE & PONTO DE EQUILÍBRIO (1º ciclo)
A3: Investimento total (R$) | B3: =Premissas!B5 -> 5000
A4: Material / 1º lote (R$) | B4: =Premissas!B3 -> 3000
A5: Marketing & teste (R$) | B5: =Premissas!B4 -> 2000
A6: Unidades produzidas no 1º lote (un) | B6: =Premissas!B9 -> 66
A7: Preço de venda (R$) | B7: =Premissas!B7 -> 119
A8: Contribuição/un vendida — blended, excl. produto (R$) | B8: ='Unit Economics'!D10 -> 101.799
A9: Margem de contribuição/un — blended, com produto (R$) | B9: ='Unit Economics'!D12 -> 56.799
A11: PONTO DE EQUILÍBRIO (recuperar o investimento)
A12: Unidades p/ recuperar os R$ 5.000 (un) | B12: =ROUNDUP(B3/B8,0) -> 50
A13: % do 1º lote que precisa vender p/ recuperar | B13: =B12/B6 -> 0.75757576
A15: CENÁRIO: vender 100% do 1º lote
A16: Receita bruta (R$) | B16: =B6*B7 -> 7854
A17: (−) Custos variáveis de venda (R$) | B17: =B6*(B7-B8) -> 1135.266
A18: (−) Custo do produto (lote vendido) (R$) | B18: =B6*Premissas!$B$8 -> 2970
A19: (−) Marketing & teste (R$) | B19: =B5 -> 2000
A20: (−) DAS MEI no ciclo (R$) | B20: =Premissas!$B$21*Premissas!$B$22 -> 240
A21: (=) Lucro líquido do 1º ciclo (R$) | B21: =B16-B17-B18-B19-B20 -> 1508.734
A22: ROI sobre o investimento (%) | B22: =B21/B3 -> 0.3017468
A23: Lucro por unidade vendida no ciclo (R$) | B23: =B21/B6 -> 22.859606
A25: Reposição (2º lote+): o produto já está validado e a verba de teste já foi paga. Cada venda direta passa a render a margem de contribuição cheia. É aqui — e migrando a produção p/ a China na Fase 2 (custo R$ 25–33/un) — que o lucro escala.
A26: Nota: sobra de orçamento por arredondamento de unidades é desprezada.

Sheet Cenários
A1: CENÁRIOS — 1º ciclo (R$ 5.000)
B2: Conservador | C2: Base | D2: Otimista
A3: ENTRADAS
A4: Preço de venda (R$) | B4: 99 | C4: 119 | D4: 129
A5: Custo unitário (R$) | B5: 52 | C5: 45 | D5: 40
A6: % canal direto | B6: 0.6 | C6: 0.9 | D6: 1
A7: Sell-through do lote (%) | B7: 0.65 | C7: 0.85 | D7: 1
A8: Material / lote (R$) | B8: =Premissas!$B$3 -> 3000 | C8: =Premissas!$B$3 -> 3000 | D8: =Premissas!$B$3 -> 3000
A9: Marketing (R$) | B9: =Premissas!$B$4 -> 2000 | C9: =Premissas!$B$4 -> 2000 | D9: =Premissas!$B$4 -> 2000
A10: RESULTADO
A11: Unidades produzidas (un) | B11: =ROUNDDOWN(B8/B5,0) -> 57 | C11: =ROUNDDOWN(C8/C5,0) -> 66 | D11: =ROUNDDOWN(D8/D5,0) -> 75
A12: Unidades vendidas (un) | B12: =ROUNDDOWN(B11*B7,0) -> 37 | C12: =ROUNDDOWN(C11*C7,0) -> 56 | D12: =ROUNDDOWN(D11*D7,0) -> 75
A13: Contrib. venda/un — direto (R$) | B13: =B4-(B4*Premissas!$B$16+Premissas!$B$19+B4*Premissas!$B$20) -> 88.565 | C13: =C4-(C4*Premissas!$B$16+Premissas!$B$19+C4*Premissas!$B$20) -> 107.265 | D13: =D4-(D4*Premissas!$B$16+Premissas!$B$19+D4*Premissas!$B$20) -> 116.615
A14: Contrib. venda/un — marketplace (R$) | B14: =B4-(B4*Premissas!$B$13+Premissas!$B$14+Premissas!$B$15+Premissas!$B$19+B4*Premissas!$B$20) -> 36.705 | C14: =C4-(C4*Premissas!$B$13+Premissas!$B$14+Premissas!$B$15+Premissas!$B$19+C4*Premissas!$B$20) -> 52.605 | D14: =D4-(D4*Premissas!$B$13+Premissas!$B$14+Premissas!$B$15+Premissas!$B$19+D4*Premissas!$B$20) -> 60.555
A15: Contrib. venda/un — blended (R$) | B15: =B13*B6+B14*(1-B6) -> 67.821 | C15: =C13*C6+C14*(1-C6) -> 101.799 | D15: =D13*D6+D14*(1-D6) -> 116.615
A16: MC/un blended (com produto) (R$) | B16: =B15-B5 -> 15.821 | C16: =C15-C5 -> 56.799 | D16: =D15-D5 -> 76.615
A17: Receita bruta (R$) | B17: =B12*B4 -> 3663 | C17: =C12*C4 -> 6664 | D17: =D12*D4 -> 9675
A18: (−) Custos variáveis de venda (R$) | B18: =B12*(B4-B15) -> 1153.623 | C18: =C12*(C4-C15) -> 963.256 | D18: =D12*(D4-D15) -> 928.875
A19: (−) COGS produto vendido (R$) | B19: =B12*B5 -> 1924 | C19: =C12*C5 -> 2520 | D19: =D12*D5 -> 3000
A20: (−) Estoque encalhado (R$) | B20: =(B11-B12)*B5 -> 1040 | C20: =(C11-C12)*C5 -> 450 | D20: =(D11-D12)*D5 -> 0
A21: (−) Marketing (R$) | B21: =B9 -> 2000 | C21: =C9 -> 2000 | D21: =D9 -> 2000
A22: (−) DAS MEI no ciclo (R$) | B22: =Premissas!$B$21*Premissas!$B$22 -> 240 | C22: =Premissas!$B$21*Premissas!$B$22 -> 240 | D22: =Premissas!$B$21*Premissas!$B$22 -> 240
A23: (=) Lucro líquido do ciclo (R$) | B23: =B17-B18-B19-B20-B21-B22 -> -2694.623 | C23: =C17-C18-C19-C20-C21-C22 -> 490.744 | D23: =D17-D18-D19-D20-D21-D22 -> 3506.125
A24: ROI sobre R$ 5.000 (%) | B24: =B23/(B8+B9) -> -0.5389246 | C24: =C23/(C8+C9) -> 0.0981488 | D24: =D23/(D8+D9) -> 0.701225
A25: Lucro/un vendida (R$) | B25: =IF(B12=0,0,B23/B12) -> -72.827649 | C25: =IF(C12=0,0,C23/C12) -> 8.7632857 | D25: =IF(D12=0,0,D23/D12) -> 46.748333
A27: Leitura: o Conservador (preço baixo + custo alto + marketplace pesado + baixa venda) destrói capital. A disciplina — preço ≥ R$ 119, venda direta, controle de custo (Tier B) e pré-venda p/ garantir sell-through — é o que torna o R$ 5.000 viável.

Sheet Projeção 12M
A1: PROJEÇÃO 12 MESES (ilustrativa — edite as unidades e o marketing)
B2: M1 | C2: M2 | D2: M3 | E2: M4 | F2: M5 | G2: M6 | H2: M7 | I2: M8 | J2: M9 | K2: M10 | L2: M11 | M2: M12 | N2: Total
A3: Unidades vendidas (un) | B3: 20 | C3: 24 | D3: 28 | E3: 32 | F3: 36 | G3: 40 | H3: 44 | I3: 48 | J3: 52 | K3: 56 | L3: 60 | M3: 64 | N3: =SUM(B3:M3) -> 504
A4: Receita bruta (R$) | B4: =B3*Premissas!$B$7 -> 2380 | C4: =C3*Premissas!$B$7 -> 2856 | D4: =D3*Premissas!$B$7 -> 3332 | E4: =E3*Premissas!$B$7 -> 3808 | F4: =F3*Premissas!$B$7 -> 4284 | G4: =G3*Premissas!$B$7 -> 4760 | H4: =H3*Premissas!$B$7 -> 5236 | I4: =I3*Premissas!$B$7 -> 5712 | ... M4: =M3*Premissas!$B$7 -> 7616 | N4: =SUM(B4:M4) -> 59976
A5: Margem de contribuição (R$) | B5: =B3*'Unit Economics'!$D$12 -> 1135.98 | C5: =C3*'Unit Economics'!$D$12 -> 1363.176 | D5: =D3*'Unit Economics'!$D$12 -> 1590.372 | E5: =E3*'Unit Economics'!$D$12 -> 1817.568 | F5: =F3*'Unit Economics'!$D$12 -> 2044.764 | G5: =G3*'Unit Economics'!$D$12 -> 2271.96 | H5: =H3*'Unit Economics'!$D$12 -> 2499.156 | I5: =I3*'Unit Economics'!$D$12 -> 2726.352 | ... M5: =M3*'Unit Economics'!$D$12 -> 3635.136 | N5: =SUM(B5:M5) -> 28626.696
A6: (−) Marketing (R$) | B6: 2000 | C6: 400 | D6: 400 | E6: 400 | F6: 500 | G6: 500 | H6: 500 | I6: 600 | J6: 600 | K6: 700 | L6: 700 | M6: 800 | N6: =SUM(B6:M6) -> 8100
A7: (−) DAS MEI (R$) | B7: =Premissas!$B$21 -> 80 | C7: =Premissas!$B$21 -> 80 | D7: =Premissas!$B$21 -> 80 | E7: =Premissas!$B$21 -> 80 | F7: =Premissas!$B$21 -> 80 | G7: =Premissas!$B$21 -> 80 | H7: =Premissas!$B$21 -> 80 | I7: =Premissas!$B$21 -> 80 | ... M7: =Premissas!$B$21 -> 80 | N7: =SUM(B7:M7) -> 960
A8: (=) Resultado do mês (R$) | B8: =B5-B6-B7 -> -944.02 | C8: =C5-C6-C7 -> 883.176 | D8: =D5-D6-D7 -> 1110.372 | E8: =E5-E6-E7 -> 1337.568 | F8: =F5-F6-F7 -> 1464.764 | G8: =G5-G6-G7 -> 1691.96 | H8: =H5-H6-H7 -> 1919.156 | I8: =I5-I6-I7 -> 2046.352 | ... M8: =M5-M6-M7 -> 2755.136 | N8: =SUM(B8:M8) -> 19566.696
A9: Resultado acumulado (R$) | B9: =B8 -> -944.02 | C9: =B9+C8 -> -60.844 | D9: =C9+D8 -> 1049.528 | E9: =D9+E8 -> 2387.096 | F9: =E9+F8 -> 3851.86 | G9: =F9+G8 -> 5543.82 | H9: =G9+H8 -> 7462.976 | I9: =H9+I8 -> 9509.328 | J9: =I9+J8 -> 11782.876 | ... M9: =L9+M8 -> 19566.696
A11: Convenção: o caixa de partida é o investimento de R$ 5.000. R$ 3.000 viram estoque (recuperado via margem conforme as vendas) e os R$ 2.000 de teste entram no Mês 1. Payback = mês em que o "Resultado acumulado" cruza zero. Assume reposição make-to-demand. Valores ILUSTRATIVOS — ajuste as unidades e o marketing.
