Workbook

Sheet Sobre
B2: ESTUDO DE VIABILIDADE ECONÔMICA — PROJETO PLANNERS (v2, reconstruído)
B3: Dois SKUs perpétuos premium (Concurseiro R$119 / Treino R$109) · lançamento em paralelo · operação D2C a partir de Brasília/DF.
B4: Investimento inicial R$ 5.000 (é o teste; há aporte conforme tração) · Fase 1 produção nacional · câmbio de planejamento USD/BRL ≈ R$ 5,20 · 19/jun/2026.
B6: COMO USAR
B7: 1. Edite apenas as células AZUIS na aba 'Premissas'. Todo o resto recalcula.
B8: 2. 'Unit Economics' mostra a margem por canal (Direto x Mercado Livre x Shopee x Blended).
B9: 3. 'Viabilidade' responde: o 1º lote recupera o investimento? E quantas unidades/mês cobrem o pró-labore?
B10: 4. 'Cenários' compara Conservador/Base/Otimista no ANO 1, com dupla linha: antes e depois do pró-labore.
B11: 5. 'Sensibilidade' mostra o resultado do ano 1 variando unidades x preço — onde o plano vira ou não.
B12: 6. 'Projeção 12M' traça a trajetória mês a mês, com ramp começando do ZERO (construção de audiência) e pró-labore a partir do mês 5.
B14: O QUE MUDOU vs. o rascunho
B15: • PRÓ-LABORE incluído: R$ 1.000 por sócio (2 sócios) a partir do mês 5 — o rascunho ignorava a retirada dos donos.
... B27: Estimativas para apoio à decisão dos sócios. Custos de produção a confirmar por 3 orçamentos de gráfica; tributos/MEI por contador. Não é recomendação financeira.

Sheet Premissas
A1: PREMISSAS — edite apenas as células azuis
A2: Investimento inicial
A3: Material / 1º lote (R$) | B3: 3000 | C3: micro-lote ~50-80 un em gráfica BR
A4: Conteúdo + amostras + seeding (R$) | B4: 800 | C4: fotos, brindes a micro-perfis de nicho
A5: Mídia paga inicial — retargeting, a partir do mês 4 (R$) | B5: 800 | C5: NÃO usar em tráfego frio
A6: Reserva operacional (R$) | B6: 400
A7: Investimento inicial total (R$) | B7: =B3+B4+B5+B6 | C7: é o teste; há aporte conforme tração
A8: Produto & preço
A9: Preço de venda — Concurseiro (R$) | B9: 119 | C9: ~paridade com Juspodivm; perpétuo = vantagem
A10: Preço de venda — Treino de Força (R$) | B10: 109 | C10: abaixo de importados (R$130-200) e apps (R$130-165/ano)
A11: % do mix de vendas em Concurseiro | B11: 0.5 | C11: lançamento equilibrado nos dois SKUs
A12: Preço médio ponderado (R$) | B12: =B9*B11+B10*(1-B11)
A13: Custo/un — 1º micro-lote <100 un (R$) | B13: 55 | C13: faixa gráfica BR 100un: R$40-65 (sourcing-tributos.md)
A14: Custo/un — reposição ≥300 un (R$) | B14: 45 | C14: Tier B; cai com volume
A15: Canais de venda
A16: % vendas — canal direto | B16: 0.9 | C16: Instagram + checkout próprio + pix
A17: % vendas — marketplace | B17: =1-B16
A18: Comissão Mercado Livre Clássico (%) | B18: 0.14 | C18: Clássico 11-14%; sem taxa fixa ≥R$79
A19: Comissão Shopee (%) | B19: 0.14 | C19: faixa R$100-199,99
A20: Taxa fixa Shopee (R$/item) | B20: 20 | C20: R$20 na faixa R$100-199,99 (mar/2026)
A21: Frete grátis marketplace — custo loja (R$/venda) | B21: 18 | C21: frete grátis efetivamente exigido
A22: Taxa de pagamento — canal direto (%) | B22: 0.025 | C22: blend pix (~1%) / cartão (~4%)
A23: Frete canal direto pago pela loja (R$) | B23: 0 | C23: cliente paga; ver sensibilidade p/ frete grátis
A24: Operacional & tributário
A25: Embalagem & manuseio (R$/pedido) | B25: 4
A26: Provisão devoluções/perdas (%) | B26: 0.04
A27: DAS MEI mensal (R$) | B27: 81 | C27: CONFIRMAR 2026 (~5% do salário mín. + R$1)
A28: Remuneração dos sócios (antes ignorada)
A29: Pró-labore por sócio (R$/mês) | B29: 1000 | C29: mínimo combinado a partir do mês 5
A30: Nº de sócios | B30: 2
A31: Mês de início do pró-labore | B31: 5 | C31: reinveste 100% nos meses 1-4
A32: Pró-labore mensal total (R$) | B32: =B29*B30
A33: Aquisição (audiência do zero)
A34: CAC orgânico (R$/cliente) | B34: 0 | C34: custo é tempo; forte do time = conteúdo
A35: CAC pago — retargeting (R$/cliente) | B35: 40 | C35: só audiência quente; tráfego frio R$120-333 inviável

Sheet Unit Economics
A1: UNIT ECONOMICS (por unidade vendida) — R$
B2: Canal Direto | C2: Merc. Livre | D2: Shopee | E2: Blended (90% Dir/10% ML)
A3: Preço de venda | B3: =Premissas!$B$12 | C3: =Premissas!$B$12 | D3: =Premissas!$B$12 | E3: =B3*Premissas!$B$16+C3*Premissas!$B$17
A4: (−) Comissão marketplace | B4: 0 | C4: =C3*Premissas!$B$18 | D4: =D3*Premissas!$B$19 | E4: =B4*Premissas!$B$16+C4*Premissas!$B$17
A5: (−) Taxa fixa marketplace | B5: 0 | C5: 0 | D5: =Premissas!$B$20 | E5: =B5*Premissas!$B$16+C5*Premissas!$B$17
A6: (−) Frete (custo p/ loja) | B6: =Premissas!$B$23 | C6: =Premissas!$B$21 | D6: =Premissas!$B$21 | E6: =B6*Premissas!$B$16+C6*Premissas!$B$17
A7: (−) Taxa de pagamento | B7: =B3*Premissas!$B$22 | C7: 0 | D7: 0 | E7: =B7*Premissas!$B$16+C7*Premissas!$B$17
A8: (−) Embalagem & manuseio | B8: =Premissas!$B$25 | C8: =Premissas!$B$25 | D8: =Premissas!$B$25 | E8: =B8*Premissas!$B$16+C8*Premissas!$B$17
A9: (−) Provisão devoluções | B9: =B3*Premissas!$B$26 | C9: =C3*Premissas!$B$26 | D9: =D3*Premissas!$B$26 | E9: =B9*Premissas!$B$16+C9*Premissas!$B$17
A10: (=) Contribuição/un (excl. produto) | B10: =B3-SUM(B4:B9) | C10: =C3-SUM(C4:C9) | D10: =D3-SUM(D4:D9) | E10: =B10*Premissas!$B$16+C10*Premissas!$B$17
A11: (−) Custo do produto (reposição) | B11: =Premissas!$B$14 | C11: =Premissas!$B$14 | D11: =Premissas!$B$14 | E11: =B11*Premissas!$B$16+C11*Premissas!$B$17
A12: (=) Margem de contribuição/un | B12: =B10-B11 | C12: =C10-C11 | D12: =D10-D11 | E12: =B12*Premissas!$B$16+C12*Premissas!$B$17
A13: Margem de contribuição (%) | B13: =B12/B3 | C13: =C12/C3 | D13: =D12/D3 | E13: =E12/E3
A15: Direto preserva ~50% de margem; Shopee (14% + R$20 fixos + frete) quase zera. Fase 1 = vender direto; marketplace só para visibilidade.

Sheet Viabilidade
A1: VIABILIDADE & PONTO DE EQUILÍBRIO
A3: Investimento total (R$) | B3: =Premissas!B7
A4: Preço médio ponderado (R$) | B4: =Premissas!B12
A5: Unidades no 1º lote (custo micro) | B5: =ROUNDDOWN(Premissas!B3/Premissas!B13,0)
A6: Contribuição/un — blended, excl. produto (R$) | B6: ='Unit Economics'!E10
A7: Margem de contribuição/un — blended (R$) | B7: ='Unit Economics'!E12
A9: Break-even do investimento (1º ciclo)
A10: Unidades p/ recuperar o investimento | B10: =ROUNDUP(B3/B6,0)
A11: % do 1º lote que precisa vender | B11: =B10/B5
A13: Break-even operacional mensal (cobrir os donos)
A14: Custo fixo mensal: pró-labore + DAS (R$) | B14: =Premissas!B32+Premissas!B27
A15: Unidades/mês p/ break-even (com pró-labore) | B15: =ROUNDUP(B14/B7,0)
A16: Receita/mês no break-even (R$) | B16: =B15*B4
A18: O 1º lote prova demanda. O teste de viabilidade REAL é a linha de cima: ~38 un/mês cobrem o pró-labore dos dois sócios (mês 5+). Ver 'Projeção 12M'.

Sheet Cenários
A1: CENÁRIOS — Ano 1 (lançamento dos 2 SKUs em paralelo)
B2: Conservador | C2: Base | D2: Otimista
A3: ENTRADAS
A4: Unidades vendidas no ano 1 (un) | B4: 180 | C4: 360 | D4: 650
A5: Preço médio (R$) | B5: 109 | C5: 114 | D5: 119
A6: Custo/un (R$) | B6: 52 | C6: 45 | D6: 40
A7: % canal direto | B7: 0.8 | C7: 0.9 | D7: 0.95
A8: Marketing no ano (R$) | B8: 1500 | C8: 2400 | D8: 3600
A9: Meses com pró-labore (5–12) | B9: 8 | C9: 8 | D9: 8
A10: RESULTADO
A11: Contrib/un direto, excl. produto (R$) | B11: =B5-(B5*Premissas!$B$22+Premissas!$B$25+B5*Premissas!$B$26+Premissas!$B$23) | C11: =C5-(C5*Premissas!$B$22+Premissas!$B$25+C5*Premissas!$B$26+Premissas!$B$23) | D11: =D5-(D5*Premissas!$B$22+Premissas!$B$25+D5*Premissas!$B$26+Premissas!$B$23)
A12: Contrib/un marketplace (ML), excl. produto (R$) | B12: =B5-(B5*Premissas!$B$18+Premissas!$B$25+Premissas!$B$21+B5*Premissas!$B$26) | C12: =C5-(C5*Premissas!$B$18+Premissas!$B$25+Premissas!$B$21+C5*Premissas!$B$26) | D12: =D5-(D5*Premissas!$B$18+Premissas!$B$25+Premissas!$B$21+D5*Premissas!$B$26)
A13: Contrib/un blended, excl. produto (R$) | B13: =B11*B7+B12*(1-B7) | C13: =C11*C7+C12*(1-C7) | D13: =D11*D7+D12*(1-D7)
A14: Margem de contribuição/un (com produto) (R$) | B14: =B13-B6 | C14: =C13-C6 | D14: =D13-D6
A15: Receita bruta (R$) | B15: =B4*B5 | C15: =C4*C5 | D15: =D4*D5
A16: Margem de contribuição total (R$) | B16: =B4*B14 | C16: =C4*C14 | D16: =D4*D14
A17: (−) Marketing (R$) | B17: =B8 | C17: =C8 | D17: =D8
A18: (−) DAS MEI no ano (12m) (R$) | B18: =Premissas!$B$27*12 | C18: =Premissas!$B$27*12 | D18: =Premissas!$B$27*12
A19: (=) Geração de caixa ANTES do pró-labore (R$) | B19: =B16-B17-B18 | C19: =C16-C17-C18 | D19: =D16-D17-D18
A20: (−) Pró-labore retirado no ano (R$) | B20: =B9*Premissas!$B$32 | C20: =C9*Premissas!$B$32 | D20: =D9*Premissas!$B$32
A21: (=) Resultado DEPOIS do pró-labore (R$) | B21: =B19-B20 | C21: =C19-C20 | D21: =D19-D20
A22: ROI do capital (caixa antes pró-labore / invest.) | B22: =B19/Premissas!$B$7 | C22: =C19/Premissas!$B$7 | D22: =D19/Premissas!$B$7
A24: Duas linhas de fundo: 'antes do pró-labore' = o caixa que o negócio gera (recupera o investimento de R$5k já no cenário-base). 'Depois do pró-labore' = se o negócio banca os R$2k/mês dos sócios — no ano 1 fica perto do zero (base), o que é normal num bootstrap: a auto-suficiência chega ao longo do ano (ver Projeção 12M) e escala em 2027.

Sheet Sensibilidade
A1: SENSIBILIDADE — Resultado do ano 1 DEPOIS do pró-labore (R$)
A3: Premissas fixas: custo/un R$45 · 90% direto · marketing R$2.400 · DAS 12m · pró-labore 8m × R$2.000.
A5: Unid. ano 1 ↓ / Preço médio → | B5: 104 | C5: 109 | D5: 114 | E5: 119 | F5: 124
A6: 180 | B6: =$A6*(((B$5-(B$5*Premissas!$B$22+Premissas!$B$25+B$5*Premissas!$B$26+Premissas!$B$23))*Premissas!$B$16+(B$5-(B$5*Premissas!$B$18+Premissas!$B$25+Premissas!$B$21+B$5*Premissas!$B$26))*Premissas!$B$17)-Premissas!$B$14)-2400-Premissas!$B$27*12-8*Premissas!$B$32 | C6: =$A6*(((C$5-(C$5*Premissas!$B$22+Premissas!$B$25+C$5*Premissas!$B$26+Premissas!$B$23))*Premissas!$B$16+(C$5-(C$5*Premissas!$B$18+Premissas!$B$25+Premissas!$B$21+C$5*Premissas!$B$26))*Premissas!$B$17)-Premissas!$B$14)-2400-Premissas!$B$27*12-8*Premissas!$B$32 | D6: =$A6*(((D$5-(D$5*Premissas!$B$22+Premissas!$B$25+D$5*Premissas!$B$26+Premissas!$B$23))*Premissas!$B$16+(D$5-(D$5*Premissas!$B$18+Premissas!$B$25+Premissas!$B$21+D$5*Premissas!$B$26))*Premissas!$B$17)-Premissas!$B$14)-2400-Premissas!$B$27*12-8*Premissas!$B$32 | E6: =$A6*(((E$5-(E$5*Premissas!$B$22+Premissas!$B$25+E$5*Premissas!$B$26+Premissas!$B$23))*Premissas!$B$16+(E$5-(E$5*Premissas!$B$18+Premissas!$B$25+Premissas!$B$21+E$5*Premissas!$B$26))*Premissas!$B$17)-Premissas!$B$14)-2400-Premissas!$B$27*12-8*Premissas!$B$32 | F6: =$A6*(((F$5-(F$5*Premissas!$B$22+Premissas!$B$25+F$5*Premissas!$B$26+Premissas!$B$23))*Premissas!$B$16+(F$5-(F$5*Premissas!$B$18+Premissas!$B$25+Premissas!$B$21+F$5*Premissas!$B$26))*Premissas!$B$17)-Premissas!$B$14)-2400-Premissas!$B$27*12-8*Premissas!$B$32
A7: 260 | B7: =$A7*(((B$5-(B$5*Premissas!$B$22+Premissas!$B$25+B$5*Premissas!$B$26+Premissas!$B$23))*Premissas!$B$16+(B$5-(B$5*Premissas!$B$18+Premissas!$B$25+Premissas!$B$21+B$5*Premissas!$B$26))*Premissas!$B$17)-Premissas!$B$14)-2400-Premissas!$B$27*12-8*Premissas!$B$32 | C7: =$A7*(((C$5-(C$5*Premissas!$B$22+Premissas!$B$25+C$5*Premissas!$B$26+Premissas!$B$23))*Premissas!$B$16+(C$5-(C$5*Premissas!$B$18+Premissas!$B$25+Premissas!$B$21+C$5*Premissas!$B$26))*Premissas!$B$17)-Premissas!$B$14)-2400-Premissas!$B$27*12-8*Premissas!$B$32 | D7: =$A7*(((D$5-(D$5*Premissas!$B$22+Premissas!$B$25+D$5*Premissas!$B$26+Premissas!$B$23))*Premissas!$B$16+(D$5-(D$5*Premissas!$B$18+Premissas!$B$25+Premissas!$B$21+D$5*Premissas!$B$26))*Premissas!$B$17)-Premissas!$B$14)-2400-Premissas!$B$27*12-8*Premissas!$B$32 | E7: =$A7*(((E$5-(E$5*Premissas!$B$22+Premissas!$B$25+E$5*Premissas!$B$26+Premissas!$B$23))*Premissas!$B$16+(E$5-(E$5*Premissas!$B$18+Premissas!$B$25+Premissas!$B$21+E$5*Premissas!$B$26))*Premissas!$B$17)-Premissas!$B$14)-2400-Premissas!$B$27*12-8*Premissas!$B$32 | F7: =$A7*(((F$5-(F$5*Premissas!$B$22+Premissas!$B$25+F$5*Premissas!$B$26+Premissas!$B$23))*Premissas!$B$16+(F$5-(F$5*Premissas!$B$18+Premissas!$B$25+Premissas!$B$21+F$5*Premissas!$B$26))*Premissas!$B$17)-Premissas!$B$14)-2400-Premissas!$B$27*12-8*Premissas!$B$32
A8: 340 | B8: =$A8*(((B$5-(B$5*Premissas!$B$22+Premissas!$B$25+B$5*Premissas!$B$26+Premissas!$B$23))*Premissas!$B$16+(B$5-(B$5*Premissas!$B$18+Premissas!$B$25+Premissas!$B$21+B$5*Premissas!$B$26))*Premissas!$B$17)-Premissas!$B$14)-2400-Premissas!$B$27*12-8*Premissas!$B$32 | C8: =$A8*(((C$5-(C$5*Premissas!$B$22+Premissas!$B$25+C$5*Premissas!$B$26+Premissas!$B$23))*Premissas!$B$16+(C$5-(C$5*Premissas!$B$18+Premissas!$B$25+Premissas!$B$21+C$5*Premissas!$B$26))*Premissas!$B$17)-Premissas!$B$14)-2400-Premissas!$B$27*12-8*Premissas!$B$32 | D8: =$A8*(((D$5-(D$5*Premissas!$B$22+Premissas!$B$25+D$5*Premissas!$B$26+Premissas!$B$23))*Premissas!$B$16+(D$5-(D$5*Premissas!$B$18+Premissas!$B$25+Premissas!$B$21+D$5*Premissas!$B$26))*Premissas!$B$17)-Premissas!$B$14)-2400-Premissas!$B$27*12-8*Premissas!$B$32 | E8: =$A8*(((E$5-(E$5*Premissas!$B$22+Premissas!$B$25+E$5*Premissas!$B$26+Premissas!$B$23))*Premissas!$B$16+(E$5-(E$5*Premissas!$B$18+Premissas!$B$25+Premissas!$B$21+E$5*Premissas!$B$26))*Premissas!$B$17)-Premissas!$B$14)-2400-Premissas!$B$27*12-8*Premissas!$B$32 | F8: =$A8*(((F$5-(F$5*Premissas!$B$22+Premissas!$B$25+F$5*Premissas!$B$26+Premissas!$B$23))*Premissas!$B$16+(F$5-(F$5*Premissas!$B$18+Premissas!$B$25+Premissas!$B$21+F$5*Premissas!$B$26))*Premissas!$B$17)-Premissas!$B$14)-2400-Premissas!$B$27*12-8*Premissas!$B$32
A9: 420 | B9: =$A9*(((B$5-(B$5*Premissas!$B$22+Premissas!$B$25+B$5*Premissas!$B$26+Premissas!$B$23))*Premissas!$B$16+(B$5-(B$5*Premissas!$B$18+Premissas!$B$25+Premissas!$B$21+B$5*Premissas!$B$26))*Premissas!$B$17)-Premissas!$B$14)-2400-Premissas!$B$27*12-8*Premissas!$B$32 | C9: =$A9*(((C$5-(C$5*Premissas!$B$22+Premissas!$B$25+C$5*Premissas!$B$26+Premissas!$B$23))*Premissas!$B$16+(C$5-(C$5*Premissas!$B$18+Premissas!$B$25+Premissas!$B$21+C$5*Premissas!$B$26))*Premissas!$B$17)-Premissas!$B$14)-2400-Premissas!$B$27*12-8*Premissas!$B$32 | D9: =$A9*(((D$5-(D$5*Premissas!$B$22+Premissas!$B$25+D$5*Premissas!$B$26+Premissas!$B$23))*Premissas!$B$16+(D$5-(D$5*Premissas!$B$18+Premissas!$B$25+Premissas!$B$21+D$5*Premissas!$B$26))*Premissas!$B$17)-Premissas!$B$14)-2400-Premissas!$B$27*12-8*Premissas!$B$32 | E9: =$A9*(((E$5-(E$5*Premissas!$B$22+Premissas!$B$25+E$5*Premissas!$B$26+Premissas!$B$23))*Premissas!$B$16+(E$5-(E$5*Premissas!$B$18+Premissas!$B$25+Premissas!$B$21+E$5*Premissas!$B$26))*Premissas!$B$17)-Premissas!$B$14)-2400-Premissas!$B$27*12-8*Premissas!$B$32 | F9: =$A9*(((F$5-(F$5*Premissas!$B$22+Premissas!$B$25+F$5*Premissas!$B$26+Premissas!$B$23))*Premissas!$B$16+(F$5-(F$5*Premissas!$B$18+Premissas!$B$25+Premissas!$B$21+F$5*Premissas!$B$26))*Premissas!$B$17)-Premissas!$B$14)-2400-Premissas!$B$27*12-8*Premissas!$B$32
A10: 500 | B10: =$A10*(((B$5-(B$5*Premissas!$B$22+Premissas!$B$25+B$5*Premissas!$B$26+Premissas!$B$23))*Premissas!$B$16+(B$5-(B$5*Premissas!$B$18+Premissas!$B$25+Premissas!$B$21+B$5*Premissas!$B$26))*Premissas!$B$17)-Premissas!$B$14)-2400-Premissas!$B$27*12-8*Premissas!$B$32 | C10: =$A10*(((C$5-(C$5*Premissas!$B$22+Premissas!$B$25+C$5*Premissas!$B$26+Premissas!$B$23))*Premissas!$B$16+(C$5-(C$5*Premissas!$B$18+Premissas!$B$25+Premissas!$B$21+C$5*Premissas!$B$26))*Premissas!$B$17)-Premissas!$B$14)-2400-Premissas!$B$27*12-8*Premissas!$B$32 | D10: =$A10*(((D$5-(D$5*Premissas!$B$22+Premissas!$B$25+D$5*Premissas!$B$26+Premissas!$B$23))*Premissas!$B$16+(D$5-(D$5*Premissas!$B$18+Premissas!$B$25+Premissas!$B$21+D$5*Premissas!$B$26))*Premissas!$B$17)-Premissas!$B$14)-2400-Premissas!$B$27*12-8*Premissas!$B$32 | E10: =$A10*(((E$5-(E$5*Premissas!$B$22+Premissas!$B$25+E$5*Premissas!$B$26+Premissas!$B$23))*Premissas!$B$16+(E$5-(E$5*Premissas!$B$18+Premissas!$B$25+Premissas!$B$21+E$5*Premissas!$B$26))*Premissas!$B$17)-Premissas!$B$14)-2400-Premissas!$B$27*12-8*Premissas!$B$32 | F10: =$A10*(((F$5-(F$5*Premissas!$B$22+Premissas!$B$25+F$5*Premissas!$B$26+Premissas!$B$23))*Premissas!$B$16+(F$5-(F$5*Premissas!$B$18+Premissas!$B$25+Premissas!$B$21+F$5*Premissas!$B$26))*Premissas!$B$17)-Premissas!$B$14)-2400-Premissas!$B$27*12-8*Premissas!$B$32
A11: 650 | B11: =$A11*(((B$5-(B$5*Premissas!$B$22+Premissas!$B$25+B$5*Premissas!$B$26+Premissas!$B$23))*Premissas!$B$16+(B$5-(B$5*Premissas!$B$18+Premissas!$B$25+Premissas!$B$21+B$5*Premissas!$B$26))*Premissas!$B$17)-Premissas!$B$14)-2400-Premissas!$B$27*12-8*Premissas!$B$32 | C11: =$A11*(((C$5-(C$5*Premissas!$B$22+Premissas!$B$25+C$5*Premissas!$B$26+Premissas!$B$23))*Premissas!$B$16+(C$5-(C$5*Premissas!$B$18+Premissas!$B$25+Premissas!$B$21+C$5*Premissas!$B$26))*Premissas!$B$17)-Premissas!$B$14)-2400-Premissas!$B$27*12-8*Premissas!$B$32 | D11: =$A11*(((D$5-(D$5*Premissas!$B$22+Premissas!$B$25+D$5*Premissas!$B$26+Premissas!$B$23))*Premissas!$B$16+(D$5-(D$5*Premissas!$B$18+Premissas!$B$25+Premissas!$B$21+D$5*Premissas!$B$26))*Premissas!$B$17)-Premissas!$B$14)-2400-Premissas!$B$27*12-8*Premissas!$B$32 | E11: =$A11*(((E$5-(E$5*Premissas!$B$22+Premissas!$B$25+E$5*Premissas!$B$26+Premissas!$B$23))*Premissas!$B$16+(E$5-(E$5*Premissas!$B$18+Premissas!$B$25+Premissas!$B$21+E$5*Premissas!$B$26))*Premissas!$B$17)-Premissas!$B$14)-2400-Premissas!$B$27*12-8*Premissas!$B$32 | F11: =$A11*(((F$5-(F$5*Premissas!$B$22+Premissas!$B$25+F$5*Premissas!$B$26+Premissas!$B$23))*Premissas!$B$16+(F$5-(F$5*Premissas!$B$18+Premissas!$B$25+Premissas!$B$21+F$5*Premissas!$B$26))*Premissas!$B$17)-Premissas!$B$14)-2400-Premissas!$B$27*12-8*Premissas!$B$32
A13: Leitura: abaixo de ~340 un/ano o negócio não cobre o pró-labore integral no ano 1 (esperado). A partir de ~420-500 un, o ano 1 já fecha positivo mesmo pagando os dois sócios. O preço move menos que o VOLUME — e volume = audiência. Por isso a aquisição orgânica é a alavanca nº 1.

Sheet Projeção 12M
A1: PROJEÇÃO 12 MESES (ramp do ZERO; pró-labore a partir do mês 5)
A2: Mês | B2: 1 | C2: 2 | D2: 3 | E2: 4 | F2: 5 | G2: 6 | H2: 7 | I2: 8 | J2: 9 | K2: 10 | L2: 11 | M2: 12 | N2: Total
A3: Unidades vendidas (un) | B3: 0 | C3: 0 | D3: 15 | E3: 22 | F3: 28 | G3: 32 | H3: 36 | I3: 40 | J3: 44 | K3: 50 | L3: 56 | M3: 64 | N3: =SUM(B3:M3)
A4: Receita bruta (R$) | B4: =B3*Premissas!$B$12 | C4: =C3*Premissas!$B$12 | D4: =D3*Premissas!$B$12 | E4: =E3*Premissas!$B$12 | F4: =F3*Premissas!$B$12 | G4: =G3*Premissas!$B$12 | H4: =H3*Premissas!$B$12 | I4: =I3*Premissas!$B$12 | ... M4: =M3*Premissas!$B$12 | N4: =SUM(B4:M4)
A5: Margem de contribuição (R$) | B5: =B3*'Unit Economics'!$E$12 | C5: =C3*'Unit Economics'!$E$12 | D5: =D3*'Unit Economics'!$E$12 | E5: =E3*'Unit Economics'!$E$12 | F5: =F3*'Unit Economics'!$E$12 | G5: =G3*'Unit Economics'!$E$12 | H5: =H3*'Unit Economics'!$E$12 | I5: =I3*'Unit Economics'!$E$12 | ... M5: =M3*'Unit Economics'!$E$12 | N5: =SUM(B5:M5)
A6: (−) Marketing (R$) | B6: 200 | C6: 200 | D6: 400 | E6: 350 | F6: 300 | G6: 250 | H6: 250 | I6: 200 | J6: 200 | K6: 200 | L6: 250 | M6: 300 | N6: =SUM(B6:M6)
A7: (−) DAS MEI (R$) | B7: =Premissas!$B$27 | C7: =Premissas!$B$27 | D7: =Premissas!$B$27 | E7: =Premissas!$B$27 | F7: =Premissas!$B$27 | G7: =Premissas!$B$27 | H7: =Premissas!$B$27 | I7: =Premissas!$B$27 | ... M7: =Premissas!$B$27 | N7: =SUM(B7:M7)
A8: (=) Result. operacional (antes pró-labore) (R$) | B8: =B5-B6-B7 | C8: =C5-C6-C7 | D8: =D5-D6-D7 | E8: =E5-E6-E7 | F8: =F5-F6-F7 | G8: =G5-G6-G7 | H8: =H5-H6-H7 | I8: =I5-I6-I7 | ... M8: =M5-M6-M7 | N8: =SUM(B8:M8)
A9: (−) Pró-labore (R$) | B9: =IF(B$2>=Premissas!$B$31,Premissas!$B$32,0) | C9: =IF(C$2>=Premissas!$B$31,Premissas!$B$32,0) | D9: =IF(D$2>=Premissas!$B$31,Premissas!$B$32,0) | E9: =IF(E$2>=Premissas!$B$31,Premissas!$B$32,0) | F9: =IF(F$2>=Premissas!$B$31,Premissas!$B$32,0) | G9: =IF(G$2>=Premissas!$B$31,Premissas!$B$32,0) | H9: =IF(H$2>=Premissas!$B$31,Premissas!$B$32,0) | I9: =IF(I$2>=Premissas!$B$31,Premissas!$B$32,0) | ... M9: =IF(M$2>=Premissas!$B$31,Premissas!$B$32,0) | N9: =SUM(B9:M9)
A10: (=) Resultado do mês (após pró-labore) (R$) | B10: =B8-B9 | C10: =C8-C9 | D10: =D8-D9 | E10: =E8-E9 | F10: =F8-F9 | G10: =G8-G9 | H10: =H8-H9 | I10: =I8-I9 | ... M10: =M8-M9 | N10: =SUM(B10:M10)
A11: Resultado acumulado, após pró-labore (R$) | B11: =B10 | C11: =B11+C10 | D11: =C11+D10 | E11: =D11+E10 | F11: =E11+F10 | G11: =F11+G10 | H11: =G11+H10 | I11: =H11+I10 | J11: =I11+J10 | ... M11: =L11+M10
A12: Caixa operacional acum. (antes pró-labore) (R$) | B12: =B8 | C12: =B12+C8 | D12: =C12+D8 | E12: =D12+E8 | F12: =E12+F8 | G12: =F12+G8 | H12: =G12+H8 | I12: =H12+I8 | J12: =I12+J8 | ... M12: =L12+M8
A14: Convenção: caixa de partida = R$5.000. Meses 1-2 = construção de lista de espera (vendas ~0). Lançamento no mês 3. Pró-labore (R$2.000/mês) a partir do mês 5 — por isso o resultado mensal cai no mês 5 e volta a subir conforme o volume cresce. O negócio passa a cobrir o pró-labore por volta do mês ~9-10. Valores ILUSTRATIVOS — ajuste 'Unidades' e 'Marketing'.

Sheet Pró-labore (AxB)
A1: PRÓ-LABORE — ESTRATÉGIA A (antecipada) × B (otimizadora), 3 anos
B2: Ano 1 | C2: Ano 2 | D2: Ano 3
A3: Trajetória do negócio (base — edite as células azuis)
A4: Unidades vendidas (un) | B4: 387 | C4: 1440 | D4: 3000
A5: Preço médio (R$) | B5: 114 | C5: 124 | D5: 129
A6: Custo/un (R$) [ano 3 = China ≥3.000 un] | B6: 45 | C6: 42 | D6: 33
A7: Marketing no ano (R$) | B7: 2900 | C7: 12000 | D7: 25000
A8: Tributos — % s/ receita (ano 1 = MEI fixo) | B8: 0 | C8: 0.06 | D8: 0.08
A9: Receita bruta (R$) | B9: =B4*B5 | C9: =C4*C5 | D9: =D4*D5
A10: MC/un blended (R$) | B10: =((B5-(B5*Premissas!$B$22+Premissas!$B$25+B5*Premissas!$B$26+Premissas!$B$23))*Premissas!$B$16+(B5-(B5*Premissas!$B$18+Premissas!$B$25+Premissas!$B$21+B5*Premissas!$B$26))*Premissas!$B$17)-B6 | C10: =((C5-(C5*Premissas!$B$22+Premissas!$B$25+C5*Premissas!$B$26+Premissas!$B$23))*Premissas!$B$16+(C5-(C5*Premissas!$B$18+Premissas!$B$25+Premissas!$B$21+C5*Premissas!$B$26))*Premissas!$B$17)-C6 | D10: =((D5-(D5*Premissas!$B$22+Premissas!$B$25+D5*Premissas!$B$26+Premissas!$B$23))*Premissas!$B$16+(D5-(D5*Premissas!$B$18+Premissas!$B$25+Premissas!$B$21+D5*Premissas!$B$26))*Premissas!$B$17)-D6
A11: Margem de contribuição total (R$) | B11: =B4*B10 | C11: =C4*C10 | D11: =D4*D10
A12: (−) Marketing (R$) | B12: =B7 | C12: =C7 | D12: =D7
A13: (−) Tributos (R$) | B13: =Premissas!$B$27*12 | C13: =C8*C9 | D13: =D8*D9
A14: (=) Geração de caixa ANTES do pró-labore (R$) | B14: =B11-B12-B13 | C14: =C11-C12-C13 | D14: =D11-D12-D13
A16: Estratégia A — pró-labore antecipado (R$ 2k/mês desde o mês 5)
A17: Pró-labore retirado no ano (R$) | B17: 16000 | C17: 24000 | D17: 24000
A18: Resultado do negócio após pró-labore (R$) | B18: =B14-B17 | C18: =C14-C17 | D18: =D14-D17
A19: Pró-labore acumulado — sócios (R$) | B19: =B17 | C19: =B19+C17 | D19: =C19+D17
A20: Caixa do negócio acumulado (R$) | B20: =B18 | C20: =B20+C18 | D20: =C20+D18
A22: Estratégia B — otimizadora (pró-labore só a partir do ano 2)
A23: Pró-labore/mês por sócio (referência) | B23: — | C23: R$ 500 → R$ 2.000 | D23: R$ 3.000 (cada)
A24: Pró-labore retirado no ano (R$) | B24: 0 | C24: 30000 | D24: 72000
A25: Resultado do negócio após pró-labore (R$) | B25: =B14-B24 | C25: =C14-C24 | D25: =D14-D24
A26: Pró-labore acumulado — sócios (R$) | B26: =B24 | C26: =B26+C24 | D26: =C26+D24
A27: Caixa do negócio acumulado (R$) | B27: =B25 | C27: =B27+C25 | D27: =C27+D25
A29: Comparação A × B
A30: Indicador | B30: Estratégia A | C30: Estratégia B
A31: Sócios começam a receber | B31: mês 5 | C31: mês 13 (ano 2)
A32: Pró-labore no ano 1 (R$) | B32: =B17 | C32: =B24
A33: Caixa reinvestido no negócio — ano 1 (R$) | B33: =B18 | C33: =B25
A34: Pró-labore acumulado — 3 anos (R$) | B34: =D19 | C34: =D26
A35: Caixa do negócio acumulado — 3 anos (R$) | B35: =D20 | C35: =D27
A37: Leitura: a Estratégia B mantém TODO o caixa no negócio no ano 1 (o ano mais frágil e faminto por capital) — ~R$ 17 mil vs ~R$ 1 mil da A —, acelerando a escala e a aproximação do lote China. Os sócios não retiram nada no ano 1 (exige outra renda nesse período), começam modestos no ano 2 (R$ 500→R$ 2.000 cada) e só ampliam no ano 3, quando o negócio claramente se sustenta. A trajetória de vendas é a MESMA nas duas (conservador: o reinvestimento extra da B tende a elevar ainda mais o crescimento). Ano 2-3 ILUSTRATIVOS — ajuste as células azuis. Tributos: ano 1 MEI; ano 2-3 já em ME/Simples (receita acima do teto MEI).

Sheet EVEF (5 anos)
A1: ESTUDO DE VIABILIDADE ECONÔMICO-FINANCEIRA (5 anos) — Estratégia B
B2: Ano 0 | C2: Ano 1 | D2: Ano 2 | E2: Ano 3 | F2: Ano 4 | G2: Ano 5
A3: Premissas de trajetória (edite as células azuis)
A4: Unidades vendidas (un) | C4: 387 | D4: 1440 | E4: 3000 | F4: 4800 | G4: 6800
A5: Preço médio (R$) | C5: 114 | D5: 124 | E5: 129 | F5: 134 | G5: 138
A6: Custo/un (R$) | C6: 45 | D6: 42 | E6: 33 | F6: 30 | G6: 28
A7: MC/un blended (R$) | C7: =((C5-(C5*Premissas!$B$22+Premissas!$B$25+C5*Premissas!$B$26+Premissas!$B$23))*Premissas!$B$16+(C5-(C5*Premissas!$B$18+Premissas!$B$25+Premissas!$B$21+C5*Premissas!$B$26))*Premissas!$B$17)-C6 | D7: =((D5-(D5*Premissas!$B$22+Premissas!$B$25+D5*Premissas!$B$26+Premissas!$B$23))*Premissas!$B$16+(D5-(D5*Premissas!$B$18+Premissas!$B$25+Premissas!$B$21+D5*Premissas!$B$26))*Premissas!$B$17)-D6 | E7: =((E5-(E5*Premissas!$B$22+Premissas!$B$25+E5*Premissas!$B$26+Premissas!$B$23))*Premissas!$B$16+(E5-(E5*Premissas!$B$18+Premissas!$B$25+Premissas!$B$21+E5*Premissas!$B$26))*Premissas!$B$17)-E6 | F7: =((F5-(F5*Premissas!$B$22+Premissas!$B$25+F5*Premissas!$B$26+Premissas!$B$23))*Premissas!$B$16+(F5-(F5*Premissas!$B$18+Premissas!$B$25+Premissas!$B$21+F5*Premissas!$B$26))*Premissas!$B$17)-F6 | G7: =((G5-(G5*Premissas!$B$22+Premissas!$B$25+G5*Premissas!$B$26+Premissas!$B$23))*Premissas!$B$16+(G5-(G5*Premissas!$B$18+Premissas!$B$25+Premissas!$B$21+G5*Premissas!$B$26))*Premissas!$B$17)-G6
A8: Marketing (R$) | C8: 2900 | D8: 12000 | E8: 25000 | F8: 45000 | G8: 70000
A9: Impostos s/ venda — % (ano 1 = MEI fixo) | C9: 0 | D9: 0.05 | E9: 0.07 | F9: 0.09 | G9: 0.1
A10: Pró-labore — Estratégia B (R$) | C10: 0 | D10: 30000 | E10: 72000 | F10: 96000 | G10: 120000
A11: Outras despesas (contador, software) (R$) | C11: 1200 | D11: 6000 | E11: 12000 | F11: 20000 | G11: 28000
A12: Parâmetros financeiros
A13: Investimento inicial — Ano 0 (R$) | B13: 5000
A14: Dias de estoque (capital de giro) | C14: 60
A15: Taxa de desconto — base / mín / máx | C15: 0.135 | D15: 0.12 | E15: 0.15
A16: DRE & fluxo de caixa (R$)
A17: Receita bruta | C17: =C4*C5 | D17: =D4*D5 | E17: =E4*E5 | F17: =F4*F5 | G17: =G4*G5
A18: Margem de contribuição | C18: =C4*C7 | D18: =D4*D7 | E18: =E4*E7 | F18: =F4*F7 | G18: =G4*G7
A19: (−) Marketing | C19: =C8 | D19: =D8 | E19: =E8 | F19: =F8 | G19: =G8
A20: (−) Pró-labore | C20: =C10 | D20: =D10 | E20: =E10 | F20: =F10 | G20: =G10
A21: (−) Outras despesas | C21: =C11 | D21: =D11 | E21: =E11 | F21: =F11 | G21: =G11
A22: (−) Impostos (Simples/MEI) | C22: =Premissas!$B$27*12 | D22: =D9*D17 | E22: =E9*E17 | F22: =F9*F17 | G22: =G9*G17
A23: (=) Resultado operacional | C23: =C18-C19-C20-C21-C22 | D23: =D18-D19-D20-D21-D22 | E23: =E18-E19-E20-E21-E22 | F23: =F18-F19-F20-F21-F22 | G23: =G18-G19-G20-G21-G22
A24: COGS (memo) | C24: =C4*C6 | D24: =D4*D6 | E24: =E4*E6 | F24: =F4*F6 | G24: =G4*G6
A25: Capital de giro — estoque | C25: =C24*$C$14/360 | D25: =D24*$C$14/360 | E25: =E24*$C$14/360 | F25: =F24*$C$14/360 | G25: =G24*$C$14/360
A26: (−) Δ capital de giro | C26: =C25 | D26: =D25-C25 | E26: =E25-D25 | F26: =F25-E25 | G26: =G25-F25
A27: (=) Fluxo de caixa livre | B27: =-B13 | C27: =C23-C26 | D27: =D23-D26 | E27: =E23-E26 | F27: =F23-F26 | G27: =G23-G26
A28: FCF acumulado | B28: =B27 | C28: =B28+C27 | D28: =C28+D27 | E28: =D28+E27 | F28: =E28+F27 | G28: =F28+G27
A29: FCF descontado @ base | B29: =B27 | C29: =C27/(1+$C$15)^1 | D29: =D27/(1+$C$15)^2 | E29: =E27/(1+$C$15)^3 | F29: =F27/(1+$C$15)^4 | G29: =G27/(1+$C$15)^5
A30: FCF descontado acumulado | B30: =B29 | C30: =B30+C29 | D30: =C30+D29 | E30: =D30+E29 | F30: =E30+F29 | G30: =F30+G29
A32: Indicadores de viabilidade
A33: VPL @ base (13,5%) (R$) | B33: =NPV($C$15,C27:G27)+B27
A34: VPL @ mín 12% | máx 15% (R$) | B34: =NPV($D$15,C27:G27)+B27 | C34: =NPV($E$15,C27:G27)+B27
A35: TIR (a.a.) | B35: =IRR(B27:G27)
A36: Payback descontado | B36: ano 1 (caixa descontado acumulado já positivo no ano 1)
A37: Necessidade de capital — pior caixa acum. (R$) | B37: =-MIN(B28:G28)
A39: Observações: (1) VPL/TIR são fortemente positivos porque o CAPITAL inicial (R$ 5 mil) é mínimo — o 'investimento' real é o trabalho dos sócios (pró-labore abaixo do mercado no início, Estratégia B) e o risco de execução/aquisição, não caixa. Leia a TIR com essa ressalva. (2) Anos 3–5 são ILUSTRATIVOS: dependem de escalar via China (≥3.000 un), de construir audiência e do vento do ciclo de concursos em 2027. (3) Escala 100% AUTOFINANCIADA (decisão dos sócios): sem pré-venda e sem empréstimo/aporte. Gatilho de capitalização — importar só quando caixa acumulado >= custo do lote + colchão de 3 meses (~R$ 135 mil) E volume >= ~5.000 un/ano; pelo FCF acumulado, isso ocorre no fim do ano 3/ano 4. Ponte: escalar em lotes BR offset crescentes pagos pela receita (~R$ 18-32/un no volume) — a China é opcionalidade, não necessidade; não há 'abismo' de R$ 99 mil. (4) Capital de giro modelado como estoque médio (dias editáveis); pix/pré-venda antecipa caixa e o reduz. Ajuste as células azuis.

Sheet LTV & Recorrência
A1: LTV, RECOMPRA & TAMANHO DO MERCADO RECORRENTE
B2: Concurseiro | C2: Treino de Força
A3: Recompra & LTV por cliente (edite as azuis)
A4: Planners por cliente / ano | B4: 3 | C4: 2.5 | D4: estudo dura ~3 meses → 3–4/ano; diário de treino ~4–5 meses
A5: Anos de permanência (tenure) | B5: 2 | C5: 3 | D5: concurseiro estuda ~2 anos (Censo 2025); treino é hábito mais longo
A6: Unidades por cliente (vida) | B6: =B4*B5 | C6: =C4*C5
A7: Preço (R$) | B7: 119 | C7: 109
A8: MC/un direto na recompra (R$) | B8: =B7-(B7*Premissas!$B$22+Premissas!$B$25+B7*Premissas!$B$26+Premissas!$B$23)-Premissas!$B$14 | C8: =C7-(C7*Premissas!$B$22+Premissas!$B$25+C7*Premissas!$B$26+Premissas!$B$23)-Premissas!$B$14
A9: LTV — receita (R$) | B9: =B6*B7 | C9: =C6*C7
A10: LTV — margem de contribuição (R$) | B10: =B6*B8 | C10: =C6*C8
A11: CAC alvo (R$) | B11: 50 | C11: 50
A12: LTV/CAC (margem) | B12: =B10/B11 | C12: =C10/C11 | D12: acima de 3× é saudável; recompra é o que sustenta CAC pago
A13: Tamanho do mercado RECORRENTE (anual)
A14: Base de compradores premium (pessoas) | B14: 550000 | C14: 260000 | D14: ponto médio do SAM (Conc 400–700k; Treino 150–370k)
A15: Unidades/ano — mercado (un) | B15: =B14*B4 | C15: =C14*C4
A16: R$/ano — mercado (receita) | B16: =B15*B7 | C16: =C15*C7
A17: Recompra por 1.000 clientes ativos (un/ano) | B17: =1000*B4 | C17: =1000*C4
A18: Fluxo de NOVOS clientes / ano
A19: Base ativa total (pessoas) | B19: 5000000 | C19: 1500000 | D19: Conc: 4–6M ativos; Treino: ~1,3–3M praticantes sérios/periodizados
A20: Novos entrantes / ano (= base ÷ tenure) | B20: =B19/B5 | C20: =C19/C5
A21: % elegível a planner premium | B21: 0.11 | C21: 0.18
A22: Novos compradores premium / ano | B22: =B20*B21 | C22: =C20*C21
A23: Saturação & abastecimento
A24: Sua venda/ano (ex.: SOM ano 1) | B24: 250 | C24: 200
A25: Share do mercado recorrente | B25: =B24/B15 | C25: =C24/C15
A26: Leitura: por ser CONSUMÍVEL (o concurseiro recompra 3–4×/ano), o mercado é muito maior em FLUXO do que em 'pessoas': ~2,3 milhões de un/ano (~R$ 267 mi/ano somando os dois nichos, no teto em que todos recompram no ritmo pleno). O LTV/CAC alto (~7–8× no orgânico) mostra que a RECOMPRA é o motor — e que mesmo CAC pago (R$ 120–150) cabe no LTV (~R$ 375–400 de margem). Saturação NÃO é risco por anos (share < 0,1%); o limite é AQUISIÇÃO + cadência de produção. 'Não desabastecer' = produzir por reposição make-to-demand com estoque de segurança; como o produto é perpétuo, encalhe quase não 'vence'. Premissas-chave a validar: planners/ano por cliente e % elegível (são as que mais movem o resultado).
